[
  {
    "name": "Arjun S.",
    "review": "Well-structured training and strong leadership on terrain. The team pushed us safely beyond our comfort zone."
  },
  {
    "name": "Neha R.",
    "review": "A disciplined outdoor experience with clear instruction, great planning, and excellent group support."
  },
  {
    "name": "Vikram T.",
    "review": "Professional, practical, and intense in the best way. Highly recommended for mindset and endurance training."
  },
  {
    "name": "Pooja V.",
    "review": "Professional, practical, and intense in the best way. Highly recommended for mindset and endurance training."
  }
]
